Workbook

Sheet START HERE
B2: VIRAL HOOK GENERATOR
B3: Turn Any Topic Into Hundreds of Scroll-Stopping Hook Ideas
B5: Stop staring at a blank screen trying to write the perfect hook. This spreadsheet turns hook writing into a repeatable system: choose a formula, enter your topic, generate variations, and test. It won't guarantee views or virality — nothing can. What it gives you is a fast, organized way to produce dozens of genuinely different hook options for any topic, so you always have something worth testing.
B10: WHO THIS IS FOR
B11: Instagram, TikTok & YouTube creators • Coaches & consultants • Freelancers & small-business owners • Social media managers • Digital-product sellers & affiliate marketers • Bloggers & personal brands • Entrepreneurs and beginners who feel stuck on content ideas
B14: WHAT THIS GENERATOR DOES
B15: • Turns one topic into dozens of unique, genuinely different hook variations
B16: • Combines your niche, topic, audience problem, desired outcome, a hook formula, an angle, a tone and a platform
B17: • Organizes 120+ proven hook formulas, 50+ niches, 110+ pain points, 110+ desired outcomes and 55+ content angles into one system
B18: • Gives you a place to track which hooks you actually test, and what happens when you do
B20: 3-STEP QUICK START
B21: 1 | C21: Open the HOOK GENERATOR tab — Type your niche, topic, audience, pain point and desired outcome into the yellow input cells.
B22: 2 | C22: Choose your formula, angle, tone & platform — Use the dropdowns. Not sure? Browse the HOOK FORMULA LIBRARY tab for ideas and examples first.
B23: 3 | C23: Generate, favorite, and test — Your variations appear instantly below. Mark your favorites, then log what you actually post in the HOOK TESTING TRACKER.
B25: THE WORKFLOW
B26: TOPIC | C26: → | D26: FORMULA | E26: → | F26: ANGLE | G26: → | H26: HOOK | I26: → | J26: TEST
B28: EXAMPLE: ONE TOPIC → FIVE DIFFERENT HOOKS
B29: Topic: "email open rates" • Niche: Email Marketing • Audience: small business owners
B30: Hook Type | C30: Example Hook
B31: Curiosity | C31: Nobody tells you this about email open rates until it's too late
B32: Mistake | C32: The subject line mistake almost every small business owner makes
B33: Question | C33: Are you making this mistake with your subject lines?
B34: Quick Win | C34: One small subject line change that made an instant difference
B35: Contrarian | C35: Unpopular opinion: your open rates aren't actually your real problem
B37: TIPS FOR CHOOSING YOUR HOOKS
B38: • Generate first, judge second — write 10-15 variations before picking a favorite
B39: • Say your hook out loud. If it's awkward to speak, it will feel awkward on camera
B40: • Match the hook's tone to the platform (see the PLATFORM GUIDE tab)
B41: • Pick 2-3 favorites per topic and actually test them, instead of endlessly generating more
B42: • Track what you post in the HOOK TESTING TRACKER so your next batch gets sharper
B43: • These are mad-libs style drafts, not finished copy — expect to lightly edit a few words for grammar before you post
B45: IMPORTANT: No hook, formula, or tool can guarantee views, followers, or sales. This system helps you generate more ideas, faster, so you can test more of them — performance always depends on your content, your audience, and the platform. Use this to work smarter, not to chase guarantees.
B49: Tabs in this workbook → Hook Generator | Formula Library | Niche & Keyword Library | Pain Points | Desired Outcomes | Content Angles | Tone Library | Platform Guide | Hook Examples | Testing Tracker | Power Words | CTA Library | 30-Day Challenge | Rewrite Tool

Sheet Hook Generator
A1: HOOK GENERATOR
A2: Fill in the yellow cells, choose your dropdowns, and your hook variations appear below automatically.
A4: STEP 1-6 -- YOUR INPUTS (yellow cells = type here)
A5: Niche | E5: e.g. Freelancing
A6: Topic / Keyword | E6: e.g. client onboarding
A7: Target Audience | E7: e.g. new freelancers
A8: Pain Point | E8: choose from dropdown or type your own
A9: Desired Outcome | E9: choose from dropdown or type your own
A10: Hook Category | E10: choose a formula category
A11: Content Angle | E11: choose your framing
A12: Tone | E12: choose your voice
A13: Platform | E13: choose your destination
A14: Number of Variations | E14: choose 5-30
A15: Suggested Keywords | B15: =IFERROR(INDEX('Niche & Keyword Library'!$C$5:$C$55,MATCH(B5,'Niche & Keyword Library'!$A$5:$A$55,0)),"Pick a niche above to see suggested keywords here") -> Pick a niche above to see suggested keywords here
A17: STEP 7-9 -- YOUR GENERATED HOOKS (edit Favorite / Status / Notes below)
A18: # | B18: Generated Hook | C18: Hook Type | D18: Angle | E18: Platform | F18: Tone | G18: Favorite | H18: Status | I18: Notes
A19: 1 | B19: =IF($B$10="","Choose a Hook Category above",IF(A19>$B$14,"",IFERROR(SUBSTITUTE(SUBSTITUTE(SUBSTITUTE(SUBSTITUTE(SUBSTITUTE(INDEX('Formula Library'!$C$5:$C$124,MATCH($B$10&"-"&(MOD(A19-1,COUNTIF('Formula Library'!$A$5:$A$124,$B$10))+1),'Formula Library'!$G$5:$G$124,0)),"[NICHE]",$B$5),"[TOPIC]",$B$6),"[PAIN]",LOWER(LEFT($B$8,1))&MID($B$8,2,500)),"[OUTCOME]",LOWER(LEFT($B$9,1))&MID($B$9,2,500)),"[AUDIENCE]",$B$7),"Add more formulas to this category in the Formula Library tab"))) -> Choose a Hook Category above | C19: =IF(A19>$B$14,"",$B$10) | D19: =IF(A19>$B$14,"",$B$11) | E19: =IF(A19>$B$14,"",$B$13) | F19: =IF(A19>$B$14,"",$B$12)
A20: 2 | B20: =IF($B$10="","Choose a Hook Category above",IF(A20>$B$14,"",IFERROR(SUBSTITUTE(SUBSTITUTE(SUBSTITUTE(SUBSTITUTE(SUBSTITUTE(INDEX('Formula Library'!$C$5:$C$124,MATCH($B$10&"-"&(MOD(A20-1,COUNTIF('Formula Library'!$A$5:$A$124,$B$10))+1),'Formula Library'!$G$5:$G$124,0)),"[NICHE]",$B$5),"[TOPIC]",$B$6),"[PAIN]",LOWER(LEFT($B$8,1))&MID($B$8,2,500)),"[OUTCOME]",LOWER(LEFT($B$9,1))&MID($B$9,2,500)),"[AUDIENCE]",$B$7),"Add more formulas to this category in the Formula Library tab"))) -> Choose a Hook Category above | C20: =IF(A20>$B$14,"",$B$10) | D20: =IF(A20>$B$14,"",$B$11) | E20: =IF(A20>$B$14,"",$B$13) | F20: =IF(A20>$B$14,"",$B$12)
A21: 3 | B21: =IF($B$10="","Choose a Hook Category above",IF(A21>$B$14,"",IFERROR(SUBSTITUTE(SUBSTITUTE(SUBSTITUTE(SUBSTITUTE(SUBSTITUTE(INDEX('Formula Library'!$C$5:$C$124,MATCH($B$10&"-"&(MOD(A21-1,COUNTIF('Formula Library'!$A$5:$A$124,$B$10))+1),'Formula Library'!$G$5:$G$124,0)),"[NICHE]",$B$5),"[TOPIC]",$B$6),"[PAIN]",LOWER(LEFT($B$8,1))&MID($B$8,2,500)),"[OUTCOME]",LOWER(LEFT($B$9,1))&MID($B$9,2,500)),"[AUDIENCE]",$B$7),"Add more formulas to this category in the Formula Library tab"))) -> Choose a Hook Category above | C21: =IF(A21>$B$14,"",$B$10) | D21: =IF(A21>$B$14,"",$B$11) | E21: =IF(A21>$B$14,"",$B$13) | F21: =IF(A21>$B$14,"",$B$12)
A22: 4 | B22: =IF($B$10="","Choose a Hook Category above",IF(A22>$B$14,"",IFERROR(SUBSTITUTE(SUBSTITUTE(SUBSTITUTE(SUBSTITUTE(SUBSTITUTE(INDEX('Formula Library'!$C$5:$C$124,MATCH($B$10&"-"&(MOD(A22-1,COUNTIF('Formula Library'!$A$5:$A$124,$B$10))+1),'Formula Library'!$G$5:$G$124,0)),"[NICHE]",$B$5),"[TOPIC]",$B$6),"[PAIN]",LOWER(LEFT($B$8,1))&MID($B$8,2,500)),"[OUTCOME]",LOWER(LEFT($B$9,1))&MID($B$9,2,500)),"[AUDIENCE]",$B$7),"Add more formulas to this category in the Formula Library tab"))) -> Choose a Hook Category above | C22: =IF(A22>$B$14,"",$B$10) | D22: =IF(A22>$B$14,"",$B$11) | E22: =IF(A22>$B$14,"",$B$13) | F22: =IF(A22>$B$14,"",$B$12)
A23: 5 | B23: =IF($B$10="","Choose a Hook Category above",IF(A23>$B$14,"",IFERROR(SUBSTITUTE(SUBSTITUTE(SUBSTITUTE(SUBSTITUTE(SUBSTITUTE(INDEX('Formula Library'!$C$5:$C$124,MATCH($B$10&"-"&(MOD(A23-1,COUNTIF('Formula Library'!$A$5:$A$124,$B$10))+1),'Formula Library'!$G$5:$G$124,0)),"[NICHE]",$B$5),"[TOPIC]",$B$6),"[PAIN]",LOWER(LEFT($B$8,1))&MID($B$8,2,500)),"[OUTCOME]",LOWER(LEFT($B$9,1))&MID($B$9,2,500)),"[AUDIENCE]",$B$7),"Add more formulas to this category in the Formula Library tab"))) -> Choose a Hook Category above | C23: =IF(A23>$B$14,"",$B$10) | D23: =IF(A23>$B$14,"",$B$11) | E23: =IF(A23>$B$14,"",$B$13) | F23: =IF(A23>$B$14,"",$B$12)
A24: 6 | B24: =IF($B$10="","Choose a Hook Category above",IF(A24>$B$14,"",IFERROR(SUBSTITUTE(SUBSTITUTE(SUBSTITUTE(SUBSTITUTE(SUBSTITUTE(INDEX('Formula Library'!$C$5:$C$124,MATCH($B$10&"-"&(MOD(A24-1,COUNTIF('Formula Library'!$A$5:$A$124,$B$10))+1),'Formula Library'!$G$5:$G$124,0)),"[NICHE]",$B$5),"[TOPIC]",$B$6),"[PAIN]",LOWER(LEFT($B$8,1))&MID($B$8,2,500)),"[OUTCOME]",LOWER(LEFT($B$9,1))&MID($B$9,2,500)),"[AUDIENCE]",$B$7),"Add more formulas to this category in the Formula Library tab"))) -> Choose a Hook Category above | C24: =IF(A24>$B$14,"",$B$10) | D24: =IF(A24>$B$14,"",$B$11) | E24: =IF(A24>$B$14,"",$B$13) | F24: =IF(A24>$B$14,"",$B$12)
A25: 7 | B25: =IF($B$10="","Choose a Hook Category above",IF(A25>$B$14,"",IFERROR(SUBSTITUTE(SUBSTITUTE(SUBSTITUTE(SUBSTITUTE(SUBSTITUTE(INDEX('Formula Library'!$C$5:$C$124,MATCH($B$10&"-"&(MOD(A25-1,COUNTIF('Formula Library'!$A$5:$A$124,$B$10))+1),'Formula Library'!$G$5:$G$124,0)),"[NICHE]",$B$5),"[TOPIC]",$B$6),"[PAIN]",LOWER(LEFT($B$8,1))&MID($B$8,2,500)),"[OUTCOME]",LOWER(LEFT($B$9,1))&MID($B$9,2,500)),"[AUDIENCE]",$B$7),"Add more formulas to this category in the Formula Library tab"))) -> Choose a Hook Category above | C25: =IF(A25>$B$14,"",$B$10) | D25: =IF(A25>$B$14,"",$B$11) | E25: =IF(A25>$B$14,"",$B$13) | F25: =IF(A25>$B$14,"",$B$12)
A26: 8 | B26: =IF($B$10="","Choose a Hook Category above",IF(A26>$B$14,"",IFERROR(SUBSTITUTE(SUBSTITUTE(SUBSTITUTE(SUBSTITUTE(SUBSTITUTE(INDEX('Formula Library'!$C$5:$C$124,MATCH($B$10&"-"&(MOD(A26-1,COUNTIF('Formula Library'!$A$5:$A$124,$B$10))+1),'Formula Library'!$G$5:$G$124,0)),"[NICHE]",$B$5),"[TOPIC]",$B$6),"[PAIN]",LOWER(LEFT($B$8,1))&MID($B$8,2,500)),"[OUTCOME]",LOWER(LEFT($B$9,1))&MID($B$9,2,500)),"[AUDIENCE]",$B$7),"Add more formulas to this category in the Formula Library tab"))) -> Choose a Hook Category above | C26: =IF(A26>$B$14,"",$B$10) | D26: =IF(A26>$B$14,"",$B$11) | E26: =IF(A26>$B$14,"",$B$13) | F26: =IF(A26>$B$14,"",$B$12)
A27: 9 | B27: =IF($B$10="","Choose a Hook Category above",IF(A27>$B$14,"",IFERROR(SUBSTITUTE(SUBSTITUTE(SUBSTITUTE(SUBSTITUTE(SUBSTITUTE(INDEX('Formula Library'!$C$5:$C$124,MATCH($B$10&"-"&(MOD(A27-1,COUNTIF('Formula Library'!$A$5:$A$124,$B$10))+1),'Formula Library'!$G$5:$G$124,0)),"[NICHE]",$B$5),"[TOPIC]",$B$6),"[PAIN]",LOWER(LEFT($B$8,1))&MID($B$8,2,500)),"[OUTCOME]",LOWER(LEFT($B$9,1))&MID($B$9,2,500)),"[AUDIENCE]",$B$7),"Add more formulas to this category in the Formula Library tab"))) -> Choose a Hook Category above | C27: =IF(A27>$B$14,"",$B$10) | D27: =IF(A27>$B$14,"",$B$11) | E27: =IF(A27>$B$14,"",$B$13) | F27: =IF(A27>$B$14,"",$B$12)
A28: 10 | B28: =IF($B$10="","Choose a Hook Category above",IF(A28>$B$14,"",IFERROR(SUBSTITUTE(SUBSTITUTE(SUBSTITUTE(SUBSTITUTE(SUBSTITUTE(INDEX('Formula Library'!$C$5:$C$124,MATCH($B$10&"-"&(MOD(A28-1,COUNTIF('Formula Library'!$A$5:$A$124,$B$10))+1),'Formula Library'!$G$5:$G$124,0)),"[NICHE]",$B$5),"[TOPIC]",$B$6),"[PAIN]",LOWER(LEFT($B$8,1))&MID($B$8,2,500)),"[OUTCOME]",LOWER(LEFT($B$9,1))&MID($B$9,2,500)),"[AUDIENCE]",$B$7),"Add more formulas to this category in the Formula Library tab"))) -> Choose a Hook Category above | C28: =IF(A28>$B$14,"",$B$10) | D28: =IF(A28>$B$14,"",$B$11) | E28: =IF(A28>$B$14,"",$B$13) | F28: =IF(A28>$B$14,"",$B$12)
A29: 11 | B29: =IF($B$10="","Choose a Hook Category above",IF(A29>$B$14,"",IFERROR(SUBSTITUTE(SUBSTITUTE(SUBSTITUTE(SUBSTITUTE(SUBSTITUTE(INDEX('Formula Library'!$C$5:$C$124,MATCH($B$10&"-"&(MOD(A29-1,COUNTIF('Formula Library'!$A$5:$A$124,$B$10))+1),'Formula Library'!$G$5:$G$124,0)),"[NICHE]",$B$5),"[TOPIC]",$B$6),"[PAIN]",LOWER(LEFT($B$8,1))&MID($B$8,2,500)),"[OUTCOME]",LOWER(LEFT($B$9,1))&MID($B$9,2,500)),"[AUDIENCE]",$B$7),"Add more formulas to this category in the Formula Library tab"))) -> Choose a Hook Category above | C29: =IF(A29>$B$14,"",$B$10) | D29: =IF(A29>$B$14,"",$B$11) | E29: =IF(A29>$B$14,"",$B$13) | F29: =IF(A29>$B$14,"",$B$12)
A30: 12 | B30: =IF($B$10="","Choose a Hook Category above",IF(A30>$B$14,"",IFERROR(SUBSTITUTE(SUBSTITUTE(SUBSTITUTE(SUBSTITUTE(SUBSTITUTE(INDEX('Formula Library'!$C$5:$C$124,MATCH($B$10&"-"&(MOD(A30-1,COUNTIF('Formula Library'!$A$5:$A$124,$B$10))+1),'Formula Library'!$G$5:$G$124,0)),"[NICHE]",$B$5),"[TOPIC]",$B$6),"[PAIN]",LOWER(LEFT($B$8,1))&MID($B$8,2,500)),"[OUTCOME]",LOWER(LEFT($B$9,1))&MID($B$9,2,500)),"[AUDIENCE]",$B$7),"Add more formulas to this category in the Formula Library tab"))) -> Choose a Hook Category above | C30: =IF(A30>$B$14,"",$B$10) | D30: =IF(A30>$B$14,"",$B$11) | E30: =IF(A30>$B$14,"",$B$13) | F30: =IF(A30>$B$14,"",$B$12)
... A48: 30 | B48: =IF($B$10="","Choose a Hook Category above",IF(A48>$B$14,"",IFERROR(SUBSTITUTE(SUBSTITUTE(SUBSTITUTE(SUBSTITUTE(SUBSTITUTE(INDEX('Formula Library'!$C$5:$C$124,MATCH($B$10&"-"&(MOD(A48-1,COUNTIF('Formula Library'!$A$5:$A$124,$B$10))+1),'Formula Library'!$G$5:$G$124,0)),"[NICHE]",$B$5),"[TOPIC]",$B$6),"[PAIN]",LOWER(LEFT($B$8,1))&MID($B$8,2,500)),"[OUTCOME]",LOWER(LEFT($B$9,1))&MID($B$9,2,500)),"[AUDIENCE]",$B$7),"Add more formulas to this category in the Formula Library tab"))) -> Choose a Hook Category above | C48: =IF(A48>$B$14,"",$B$10) | D48: =IF(A48>$B$14,"",$B$11) | E48: =IF(A48>$B$14,"",$B$13) | F48: =IF(A48>$B$14,"",$B$12)

Sheet Formula Library
A1: HOOK FORMULA LIBRARY -- 120 Formulas Across 24 Categories
A2: Browse by category, or use the Hook Category dropdown on the Hook Generator tab to pull these formulas automatically. Column G is a helper column the Hook Generator uses to look up formulas -- leave it as a formula. Add your own formulas any time; just fill in columns A-F and copy the formula down in column G.
A4: Category | B4: Formula Name | C4: Formula Template | D4: Example | E4: Best Use Case | F4: Recommended Platform | G4: Lookup Key (auto)
A5: CURIOSITY | B5: The Weird Reason | C5: The weird reason [AUDIENCE] never actually [OUTCOME] from their [TOPIC] | D5: The weird reason beginners never actually save time with their meal prep | E5: Opening a video that reveals an unexpected insight | F5: TikTok | G5: =A5&"-"&COUNTIF($A$5:A5,A5) -> CURIOSITY-1
A6: CURIOSITY | B6: Nobody Tells You | C6: Nobody tells you this about [TOPIC] until it's too late | D6: Nobody tells you this about freelance contracts until it's too late | E6: Building intrigue before a warning or lesson | F6: Instagram Reels | G6: =A6&"-"&COUNTIF($A$5:A6,A6) -> CURIOSITY-2
A7: CURIOSITY | B7: What Happens When | C7: What happens when you [TOPIC] every single day for a month | D7: What happens when you post on LinkedIn every single day for a month | E7: Experiment-style content | F7: YouTube Shorts | G7: =A7&"-"&COUNTIF($A$5:A7,A7) -> CURIOSITY-3
A8: CURIOSITY | B8: Wasn't Going To Share | C8: I wasn't going to share this [TOPIC] method, but here it is | D8: I wasn't going to share this email subject line method, but here it is | E8: Framing a tip as exclusive | F8: Instagram Reels | G8: =A8&"-"&COUNTIF($A$5:A8,A8) -> CURIOSITY-4
A9: CURIOSITY | B9: The Part Nobody Shows | C9: The part of [TOPIC] nobody shows you in [NICHE] | D9: The part of client onboarding nobody shows you in freelancing | E9: Behind-the-scenes reveal | F9: YouTube | G9: =A9&"-"&COUNTIF($A$5:A9,A9) -> CURIOSITY-5
A10: PROBLEM | B10: If This Is You | C10: If [PAIN], this is for you | D10: If you're stuck getting zero replies to cold emails, this is for you | E10: Direct pain-point targeting | F10: Instagram Reels | G10: =A10&"-"&COUNTIF($A$5:A10,A10) -> PROBLEM-1
A11: PROBLEM | B11: Still Dealing With It | C11: Still dealing with [PAIN]? Here's what's actually going on | D11: Still dealing with low engagement? Here's what's actually going on | E11: Empathy hook before a fix | F11: TikTok | G11: =A11&"-"&COUNTIF($A$5:A11,A11) -> PROBLEM-2
A12: PROBLEM | B12: The Real Reason | C12: The real reason you're dealing with [PAIN] | D12: The real reason you're dealing with inconsistent sales | E12: Diagnosing a root cause | F12: YouTube | G12: =A12&"-"&COUNTIF($A$5:A12,A12) -> PROBLEM-3
A13: PROBLEM | B13: This Is Why | C13: This is why [PAIN] keeps happening no matter what you try | D13: This is why your content ideas keep drying up no matter what you try | E13: Validating frustration before teaching | F13: Instagram Reels | G13: =A13&"-"&COUNTIF($A$5:A13,A13) -> PROBLEM-4
A14: PROBLEM | B14: You're Not Alone | C14: You're not the only [AUDIENCE] dealing with [PAIN] | D14: You're not the only coach dealing with no-shows | E14: Community-building hook | F14: Facebook | G14: =A14&"-"&COUNTIF($A$5:A14,A14) -> PROBLEM-5
A15: MISTAKE | B15: The Mistake Everyone Makes | C15: The [TOPIC] mistake almost every [AUDIENCE] makes | D15: The pricing mistake almost every freelancer makes | E15: Single-tip mistake videos | F15: TikTok | G15: =A15&"-"&COUNTIF($A$5:A15,A15) -> MISTAKE-1
A16: MISTAKE | B16: I Made This Mistake | C16: I made this [TOPIC] mistake for way too long before I caught it | D16: I made this Instagram bio mistake for way too long before I caught it | E16: Personal story into a lesson | F16: Instagram Reels | G16: =A16&"-"&COUNTIF($A$5:A16,A16) -> MISTAKE-2
... A124: MONEY-SAVING | B124: Save Money On | C124: How to save money on [TOPIC] without cutting corners | D124: How to save money on tools without cutting corners | E124: Value-focused hook | F124: Instagram Carousel | G124: =A124&"-"&COUNTIF($A$5:A124,A124) -> MONEY-SAVING-5

Sheet Niche & Keyword Library
A1: NICHE & KEYWORD LIBRARY -- 51 Niches, Fully Editable
A2: Pick your niche on the Hook Generator tab and its keywords will surface automatically as suggestions. Don't see your niche? Add a new row below -- everything here is yours to edit.
A4: Niche | B4: Category | C4: Keywords (comma-separated) | D4: Example Topic
A5: AI | B5: Technology | C5: AI tools, automation, ChatGPT, prompts, machine learning, AI workflow | D5: using AI to write faster
A6: Technology | B6: Technology | C6: apps, gadgets, software, tech tips, tech news, tech reviews | D6: apps that save you time
A7: Fitness | B7: Health | C7: workout plans, strength training, home workouts, cardio, gym tips, fitness routine | D7: a 15-minute home workout
A8: Nutrition | B8: Health | C8: meal prep, macros, healthy eating, meal planning, protein, calorie tracking | D8: simple high-protein meals
A9: Personal Finance | B9: Finance | C9: budgeting, saving money, debt payoff, money mindset, emergency fund, financial goals | D9: budgeting on a tight income
A10: Career | B10: Career | C10: job interviews, career growth, resumes, promotions, career change, workplace tips | D10: asking for a raise
A11: Job Search | B11: Career | C11: resume tips, LinkedIn profile, cover letters, job applications, networking, interview prep | D11: standing out in a job application
A12: Productivity | B12: Lifestyle | C12: time management, focus, daily routine, productivity system, habits, to-do lists | D12: a morning routine that sticks
A13: Self Improvement | B13: Lifestyle | C13: mindset, habits, discipline, goal setting, personal growth, motivation | D13: building better habits
A14: Business | B14: Business | C14: business strategy, startups, business growth, systems, operations, business planning | D14: scaling a small business
A15: Entrepreneurship | B15: Business | C15: starting a business, side hustle, founder journey, business ideas, bootstrapping, entrepreneur mindset | D15: starting a business with no funding
... A55: Side Hustles | B55: Finance | C55: extra income, side hustle ideas, part-time income, side business, freelance income, passive income ideas | D55: side hustles that fit a 9-to-5

Sheet Pain Points
A1: AUDIENCE PAIN POINTS -- 110 Ready-to-Use Pain Points
A2: Pick one on the Hook Generator tab (dropdown), or add your own audience-specific pain point in a new row.
A4: Category | B4: Pain Point
A5: Time & Consistency | B5: Not enough time to create content
A6: Time & Consistency | B6: Struggling to stay consistent with posting
A7: Time & Consistency | B7: Constantly missing content deadlines
A8: Time & Consistency | B8: Spending hours on content that barely gets seen
A9: Time & Consistency | B9: Never having a backlog of ready-to-post content
A10: Time & Consistency | B10: Feeling behind on every platform at once
A11: Time & Consistency | B11: Losing entire evenings to editing videos
A12: Time & Consistency | B12: Starting content plans and abandoning them within a week
A13: Time & Consistency | B13: Recording ten takes before something feels usable
A14: Time & Consistency | B14: Rescheduling content so often it never goes out
A15: Time & Consistency | B15: Feeling like there's never a good time to film
... A114: Money & Resources | B114: Struggling to budget around inconsistent income

Sheet Desired Outcomes
A1: DESIRED OUTCOMES -- 110 Ready-to-Use Outcomes
A2: Pick one on the Hook Generator tab (dropdown), or add your own outcome that matches what your audience wants.
A4: Category | B4: Desired Outcome
A5: Time & Efficiency | B5: Save time creating content
A6: Time & Efficiency | B6: Build a content system that runs itself
A7: Time & Efficiency | B7: Batch a month of posts in one sitting
A8: Time & Efficiency | B8: Spend less time editing without losing quality
A9: Time & Efficiency | B9: Free up evenings currently spent on content
A10: Time & Efficiency | B10: Create content faster without sacrificing quality
A11: Time & Efficiency | B11: Never run out of ready-to-post content
A12: Time & Efficiency | B12: Simplify a messy, time-consuming process
A13: Time & Efficiency | B13: Cut editing time in half
A14: Time & Efficiency | B14: Automate repetitive parts of the workflow
A15: Time & Efficiency | B15: Reclaim weekends currently lost to work
... A114: Money & Financial | B114: Track spending without a complicated system

Sheet Content Angles
A1: CONTENT ANGLES -- 55 Angles to Frame Any Hook
A2: Pick one on the Hook Generator tab (dropdown) to set the framing for your batch of hooks.
A4: Content Angle | B4: How To Use It
A5: Beginner | B5: Written for someone brand new to the topic
A6: Expert | B6: Positions you as the experienced authority
A7: Mistakes | B7: Highlights what people get wrong
A8: Quick Tips | B8: Short, fast, actionable advice
A9: Step-by-Step | B9: Walks through a clear process in order
A10: Checklist | B10: A scannable list to follow or tick off
A11: Myth vs Reality | B11: Contrasts a common belief with the truth
A12: Before vs After | B12: Shows a clear transformation or contrast
A13: Case Study | B13: Breaks down a real result or example
A14: Personal Story | B14: Shares a personal experience or moment
A15: Lessons Learned | B15: Reflects on what a past experience taught you
... A59: What I Wish I Knew Sooner | B59: Frames advice as a missed shortcut

Sheet Tone Library
A1: TONE LIBRARY -- 14 Tones
A2: Pick a tone on the Hook Generator tab to shape how every hook in that batch sounds.
A4: Tone | B4: Description | C4: Example Phrase
A5: Professional | B5: Polished, credible, and business-appropriate | C5: Here's what the data actually shows about client retention.
A6: Friendly | B6: Warm, approachable, like advice from a friend | C6: Okay, let's talk about something that trips up a lot of us.
A7: Conversational | B7: Casual, natural, like you're talking to one person | C7: So here's the thing nobody mentions about pricing.
A8: Bold | B8: Confident, assertive, unapologetic | C8: This is the strategy most people are too scared to try.
A9: Educational | B9: Clear, informative, teaching-first | C9: Here's exactly how this works, step by step.
A10: Curious | B10: Open, exploratory, inviting the audience to wonder | C10: I've been wondering why some posts just take off.
A11: Direct | B11: Blunt, no fluff, straight to the point | C11: Stop doing this. It's not working.
A12: Inspirational | B12: Uplifting, motivating, forward-looking | C12: You're closer to this than you think.
A13: Storytelling | B13: Narrative-driven, builds a scene or moment | C13: It was a Tuesday night and I was ready to quit.
A14: Expert | B14: Authoritative, backed by experience or data | C14: After years of testing this, here's what actually moves the needle.
A15: Funny | B15: Light, playful, a little self-aware | C15: My content calendar and I are not currently speaking.
... A18: Beginner-Friendly | B18: Patient, simple, assumes no prior knowledge | C18: No experience needed, we're starting from zero together.

Sheet Platform Guide
A1: PLATFORM GUIDE -- 8 Platforms
A2: General starting points, not rules. No formula or length guarantees performance -- always adapt to what your specific audience responds to.
A4: Platform | B4: Recommended Hook Style | C4: Approx. Hook Length | D4: What The Hook Should Accomplish | E4: Example
A5: Instagram Reels | B5: Fast, punchy, visual-first. Say it in the first 1-2 seconds on screen text too. | C5: 6-12 words on screen, 1-2 sentences spoken | D5: Stop the scroll and earn the next 3 seconds of watch time | E5: The mistake that's quietly killing your engagement.
A6: TikTok | B6: Native, conversational, feels unscripted rather than polished | C6: 5-10 words on screen, spoken hook under 3 seconds | D6: Interrupt the scroll with something unexpected or relatable | E6: Nobody talks about this part of freelancing.
A7: YouTube Shorts | B7: Similar to TikTok but slightly more explanatory framing works | C7: 1-2 short sentences, can be slightly longer than TikTok | D7: Earn a full watch and a reason to tap through to the channel | E7: I tried this for 30 days so you don't have to.
A8: YouTube | B8: Sets up a clear promise for the full video, can build curiosity over 10-15 seconds | C8: 1-3 sentences, often paired with a visual pattern interrupt | D8: Get the click and set expectations for the value ahead | E8: By the end of this video, you'll have a system for this.
A9: LinkedIn | B9: Professional but still human; opens with a real insight or result, not corporate speak | C9: 1 short line, often followed by a line break | D9: Earn a 'see more' click from a professional audience | E9: Here's what six months of cold outreach actually taught me.
A10: Facebook | B10: Community and relatable framing, works well with a question or shared experience | C10: 1-2 sentences, slightly longer copy performs fine | D10: Spark comments and shares within a community-style feed | E10: Anyone else feel like this every single Monday?
A11: X | B11: Short, sharp, and often opinion-led; the whole hook may be the whole post | C11: Under 280 characters, often a single strong sentence | D11: Earn a reply, repost, or click into a thread | E11: Unpopular opinion: most advice about this is wrong.
A12: Instagram Carousel | B12: The first slide has to work as a standalone hook; sets up a list or story to swipe through | C12: One bold headline line plus a short subheading | D12: Earn the first swipe and the eventual save | E12: 5 mistakes that are quietly costing you engagement.

Sheet Lists
A1: CURIOSITY | B1: 5 | C1: New | D1: Yes | E1: More Curiosity
A2: PROBLEM | B2: 10 | C2: Favorite | D2: No | E2: More Specific
A3: MISTAKE | B3: 15 | C3: Test | E3: Shorter
A4: HOW-TO | B4: 20 | C4: Used | E4: More Conversational
A5: LIST | B5: 25 | C5: Rewrite | E5: More Emotional
A6: QUESTION | B6: 30 | C6: Archive | E6: More Educational
A7: WARNING | E7: More Direct
A8: SECRET | E8: Question Format
A9: CONTRARIAN | E9: Contrarian Format
A10: MYTH-BUSTING | E10: Story Format
A11: STORY
A12: TRANSFORMATION
A13: BEFORE/AFTER
A14: COMPARISON
A15: CHALLENGE
A16: CASE STUDY
A17: PERSONAL EXPERIENCE
A18: PAIN POINT
A19: DESIRE
A20: BEGINNER
A21: ADVANCED
A22: QUICK WIN
... A24: MONEY-SAVING

Sheet Hook Examples
A1: HOOK EXAMPLES -- 208 Ready-to-Use Hooks Across 16 Niches
A2: Use these as-is, or as inspiration for your own. Filter by niche or hook type to find what fits.
A4: Niche | B4: Example Hook | C4: Hook Type
A5: AI | B5: The AI tool that quietly saves me two hours every week | C5: TIME-SAVING
A6: AI | B6: Most people are using ChatGPT wrong. Here's what actually works | C6: CONTRARIAN
A7: AI | B7: I asked AI to do my job for a day. Here's what happened | C7: CHALLENGE
A8: AI | B8: The one AI prompt I use more than any other | C8: SECRET
A9: AI | B9: Nobody tells you this about AI-generated content | C9: CURIOSITY
A10: AI | B10: 3 AI tools that replaced tasks I used to dread | C10: LIST
A11: AI | B11: This is the AI mistake that makes content sound robotic | C11: MISTAKE
A12: AI | B12: Before you pay for an AI tool, try this free version first | C12: MONEY-SAVING
A13: AI | B13: What I wish I knew about AI prompts when I started | C13: PERSONAL EXPERIENCE
A14: AI | B14: Is AI actually saving you time, or just moving the work around? | C14: QUESTION
A15: AI | B15: The AI workflow that turned one idea into a week of content | C15: TRANSFORMATION
... A212: Real Estate | B212: The advanced version of buyer follow-up nobody explains simply | C212: ADVANCED

Sheet Testing Tracker
A1: HOOK TESTING TRACKER
A2: Log every hook you actually post here. After a few weeks, sort by Views or Engagement Rate to see which hook types are working best for your audience -- there's no 'viral score', just your own real numbers over time.
A3: How to use it: (1) Post a hook. (2) Come back after 24-48 hours and fill in the metrics. (3) Every few weeks, filter by Hook Type or Platform to compare. (4) Feed what's working back into your next Hook Generator batch.
A5: Date | B5: Hook | C5: Platform | D5: Topic | E5: Views | F5: Likes | G5: Comments | H5: Shares | I5: Saves | J5: Watch Time | K5: Clicks | L5: Conversions | M5: Engagement Rate | N5: Notes
A6: 2026-01-14 | B6: Nobody tells you this about pricing until it's too late | C6: Instagram Reels | D6: freelance pricing | E6: 4200 | F6: 310 | G6: 28 | H6: 52 | I6: 96 | J6: 62% | K6: 14 | L6: 3 | M6: =IFERROR((F6+G6+H6+I6)/E6,"") -> 0.11571429 | N6: Best hook this month, testing a follow-up
M7: =IFERROR((F7+G7+H7+I7)/E7,"")
M8: =IFERROR((F8+G8+H8+I8)/E8,"")
M9: =IFERROR((F9+G9+H9+I9)/E9,"")
M10: =IFERROR((F10+G10+H10+I10)/E10,"")
M11: =IFERROR((F11+G11+H11+I11)/E11,"")
M12: =IFERROR((F12+G12+H12+I12)/E12,"")
M13: =IFERROR((F13+G13+H13+I13)/E13,"")
M14: =IFERROR((F14+G14+H14+I14)/E14,"")
M15: =IFERROR((F15+G15+H15+I15)/E15,"")
M16: =IFERROR((F16+G16+H16+I16)/E16,"")
M17: =IFERROR((F17+G17+H17+I17)/E17,"")
M18: =IFERROR((F18+G18+H18+I18)/E18,"")
... M65: =IFERROR((F65+G65+H65+I65)/E65,"")

Sheet Power Words
A1: BONUS: 100 POWER WORDS
A2: Words and short phrases you can drop into any hook to sharpen it. Grouped by what they do.
A4: Category | B4: Power Word / Phrase
A5: Curiosity | B5: secret
A6: Curiosity | B6: hidden
A7: Curiosity | B7: little-known
A8: Curiosity | B8: behind the scenes
A9: Curiosity | B9: the truth about
A10: Curiosity | B10: nobody tells you
A11: Curiosity | B11: surprising
A12: Curiosity | B12: unexpected
A13: Curiosity | B13: what if
A14: Curiosity | B14: turns out
A15: Curiosity | B15: the real reason
... A104: Problem | B104: spinning your wheels

Sheet CTA Library
A1: BONUS: 50 CTA IDEAS
A2: Natural calls to action, grouped by goal. Pick one that fits the hook you just wrote -- avoid stacking more than one per post.
A4: Category | B4: CTA
A5: Comment | B5: Comment 'READY' if you're trying this one
A6: Comment | B6: What's your biggest struggle with this? Drop it below
A7: Comment | B7: Comment your niche and I'll reply with an idea
A8: Comment | B8: Agree or disagree? Let me know in the comments
A9: Comment | B9: Tell me which one you're starting with
A10: Comment | B10: Comment 'YES' if this is you right now
A11: Comment | B11: Reply with the number that fits you best
A12: Save | B12: Save this so you have it next time you're stuck
A13: Save | B13: Save this before you scroll past it
A14: Save | B14: Bookmark this for your next content planning session
A15: Save | B15: Save this one, you'll want it later this week
... A54: Download | B54: Grab your copy and start using it this week

Sheet 30-Day Challenge
A1: BONUS: 30-DAY HOOK CHALLENGE
A2: One hook type a day for a month. Write, test, and track -- by Day 30 you'll know which formulas actually work for your audience.
A4: Day | B4: Hook Type | C4: Daily Task | D4: Content Idea | E4: Testing Note
A5: 1 | B5: CURIOSITY | C5: Write 5 Curiosity hooks about your main topic using the Hook Generator | D5: Use the Hook Generator: set Hook Category to 'CURIOSITY' and generate 5 variations for your current topic | E5: Log which of today's 5 hooks feels strongest before you publish anything
A6: 2 | B6: PROBLEM | C6: Write 5 Problem hooks naming a pain point your audience feels weekly | D6: Use the Hook Generator: set Hook Category to 'PROBLEM' and generate 5 variations for your current topic | E6: Note which pain point felt the most specific and true to your audience
A7: 3 | B7: MISTAKE | C7: Write 5 Mistake hooks about errors beginners in your niche make | D7: Use the Hook Generator: set Hook Category to 'MISTAKE' and generate 5 variations for your current topic | E7: Track whether naming a mistake directly changes your usual engagement
A8: 4 | B8: HOW-TO | C8: Write 5 How-To hooks for your most requested skill | D8: Use the Hook Generator: set Hook Category to 'HOW-TO' and generate 5 variations for your current topic | E8: Compare today's how-to hooks against your last tutorial's opening line
A9: 5 | B9: LIST | C9: Write 5 List hooks turning one idea into a numbered post | D9: Use the Hook Generator: set Hook Category to 'LIST' and generate 5 variations for your current topic | E9: See if numbered hooks get more saves than your usual format
A10: 6 | B10: QUESTION | C10: Write 5 Question hooks that prompt a comment reply | D10: Use the Hook Generator: set Hook Category to 'QUESTION' and generate 5 variations for your current topic | E10: Watch whether question hooks actually increase comments this time
A11: 7 | B11: WARNING | C11: Write 5 Warning hooks about a risk your audience should avoid | D11: Use the Hook Generator: set Hook Category to 'WARNING' and generate 5 variations for your current topic | E11: Note if warning-style hooks get faster stops in the first few seconds
A12: 8 | B12: SECRET | C12: Write 5 Secret hooks sharing something you rarely post about | D12: Use the Hook Generator: set Hook Category to 'SECRET' and generate 5 variations for your current topic | E12: Track if 'secret' framing changes how far people watch
A13: 9 | B13: CONTRARIAN | C13: Write 5 Contrarian hooks challenging common advice in your niche | D13: Use the Hook Generator: set Hook Category to 'CONTRARIAN' and generate 5 variations for your current topic | E13: Log any pushback or extra engagement on your contrarian take
A14: 10 | B14: MYTH-BUSTING | C14: Write 5 Myth-Busting hooks correcting a misconception | D14: Use the Hook Generator: set Hook Category to 'MYTH-BUSTING' and generate 5 variations for your current topic | E14: See if correcting a myth gets shared more than a standard tip
A15: 11 | B15: STORY | C15: Write 5 Story hooks opening with a real moment from your work | D15: Use the Hook Generator: set Hook Category to 'STORY' and generate 5 variations for your current topic | E15: Note whether story hooks hold watch time longer than list hooks
A16: 12 | B16: TRANSFORMATION | C16: Write 5 Transformation hooks about a before-and-after result | D16: Use the Hook Generator: set Hook Category to 'TRANSFORMATION' and generate 5 variations for your current topic | E16: Compare engagement on this transformation hook to a plain how-to
... A34: 30 | B34: QUESTION | C34: Publish, log the results, and set your top 3 formulas to reuse going forward | D34: Use the Hook Generator: set Hook Category to 'QUESTION' and generate 5 variations for your current topic | E34: Set your default hook formula for next month based on this month's data

Sheet Rewrite Tool
A1: BONUS: HOOK REWRITE TOOL
A2: Paste a hook that isn't landing, then rewrite it 10 different ways using the techniques below. You'll almost always find a stronger version by the third or fourth attempt.
A4: Original Hook:
A6: Rewrite Technique | B6: How To Apply It | C6: Example Transformation | D6: Your Rewrite
A7: More Curiosity | B7: Remove the answer from the hook, keep only the reason to keep watching | C7: Before: "5 tips to grow your Instagram" -> After: "The one Instagram habit almost nobody talks about"
A8: More Specific | B8: Swap a vague word for an exact number, name, or detail | C8: Before: "How to get more clients" -> After: "How I booked 3 new clients from one Instagram post"
A9: Shorter | B9: Cut it down to under 8 words without losing the point | C9: Before: "If you have been struggling to figure out how to grow your email list, here's what worked" -> After: "The email list growth trick nobody mentions"
A10: More Conversational | B10: Say it the way you'd say it out loud to a friend | C10: Before: "Implementing this strategy will optimize your results" -> After: "Okay, this one thing actually made a difference"
A11: More Emotional | B11: Name the feeling your audience has, not just the topic | C11: Before: "Tips for managing your time better" -> After: "Tired of feeling behind before the day even starts?"
A12: More Educational | B12: Lead with the insight or mechanism, not just the topic | C12: Before: "Content tips for beginners" -> After: "Here's exactly why your hooks aren't landing yet"
A13: More Direct | B13: Cut the setup and state the point immediately | C13: Before: "So I wanted to talk today about something that's been on my mind" -> After: "Stop doing this in your first three seconds"
A14: Question Format | B14: Turn the statement into a question the viewer answers in their head | C14: Before: "This mistake is costing you engagement" -> After: "Is this mistake quietly costing you engagement?"
A15: Contrarian Format | B15: State the opposite of common advice, then explain why | C15: Before: "Post every day to grow faster" -> After: "Posting every day might be slowing your growth down"
A16: Story Format | B16: Open with a moment in time instead of a statement | C16: Before: "Here are 3 lessons about pricing" -> After: "I almost undercharged my biggest client. Here's what stopped me"
